octorun/__init__.py
octorun/cli.py
octorun/default_config.json
octorun/gpu_benchmark.py
octorun/lock_manager.py
octorun/py.typed
octorun/runner.py
octorun/benchmarks/__init__.py
octorun/benchmarks/compute_benchmark.py
octorun/benchmarks/memory_benchmark.py
octorun-0.2.0.dist-info/METADATA
octorun-0.2.0.dist-info/WHEEL
octorun-0.2.0.dist-info/entry_points.txt
octorun-0.2.0.dist-info/licenses/LICENSE
octorun-0.2.0.dist-info/RECORD
