Metadata-Version: 2.4
Name: octorun
Version: 0.2.0
Summary: A command-line tool for distributed parallel execution across multiple GPUs
Project-URL: Homepage, https://github.com/HarborYuan/OctoRun
Project-URL: Repository, https://github.com/HarborYuan/OctoRun
Author-email: Haobo Yuan <haoboyuan@ucmerced.edu>
Maintainer-email: Haobo Yuan <haoboyuan@ucmerced.edu>
License: MIT
License-File: LICENSE
Keywords: cli,deep-learning,distributed,gpu,parallel
Requires-Python: >=3.10
Requires-Dist: torch>=2.0
Provides-Extra: dev
Requires-Dist: pytest>=7.0; extra == 'dev'
